net_genconfig/__init__.py
net_genconfig/__main__.py
net_genconfig/helpers.py
net_genconfig/netaddr_filter.py
net_genconfig-2.2.3.0.dist-info/LICENSE
net_genconfig-2.2.3.0.dist-info/METADATA
net_genconfig-2.2.3.0.dist-info/WHEEL
net_genconfig-2.2.3.0.dist-info/top_level.txt
net_genconfig-2.2.3.0.dist-info/RECORD
