Metadata-Version: 2.1
Name: net-genconfig
Version: 2.2.3.0
Summary: Network device configuration generator
Home-page: https://gitlab.developers.cam.ac.uk/uis/netsys/udn/net-genconfig
Author: Robert Franklin
Author-email: rcf34@cam.ac.uk
Classifier: Programming Language :: Python :: 3
Classifier: License :: OSI Approved :: MIT License
Classifier: Operating System :: OS Independent
License-File: LICENSE
Requires-Dist: deepops
Requires-Dist: jinja2
Requires-Dist: netaddr >=0.10.1
Requires-Dist: net-inventorylib >=2.1.1
Requires-Dist: pyyaml
